AUTHORS.rst
CHANGELOG.rst
LICENSE
MANIFEST.in
README.rst
setup.py
generic/__init__.py
generic/admin.py
generic/backends.py
generic/forms.py
generic/generator.py
generic/loaders.py
generic/models.py
generic/tests.py
generic/urls.py
generic/views.py
generic/widgets.py
generic/static/basic/.DS_Store
generic/static/basic/css/jmbo.css
generic/static/basic/pics/.DS_Store
generic/static/basic/pics/accept.png
generic/static/basic/pics/article-pic.jpg
generic/static/basic/pics/favicon.gif
generic/static/basic/pics/favicon.ico
generic/static/basic/pics/fb-login.png
generic/static/basic/pics/fb.png
generic/static/basic/pics/generic-avatar.jpg
generic/static/basic/pics/logo.jpg
generic/static/basic/pics/og_jmbo_logo.png
generic/static/basic/pics/og_panya_logo.png
generic/static/basic/pics/sign-in-with-twitter-l.png
generic/static/basic/pics/thumb.png
generic/static/basic/pics/thumb1.jpg
generic/static/basic/pics/thumb2.jpg
generic/static/basic/pics/thumb3.jpg
generic/static/basic/pics/thumb4.jpg
generic/static/basic/pics/thumb7.jpg
generic/static/basic/pics/thumb8.jpg
generic/static/basic/pics/tw.png
generic/static/basic/pics/warning.png
generic/templates/basic/base.html
generic/templates/basic/category/detail.html
generic/templates/basic/category/list.html
generic/templates/basic/generic/home.html
generic/templates/basic/generic/join.html
generic/templates/basic/generic/inclusion_tags/element_listing.html
generic/templates/basic/generic/inclusion_tags/element_promo.html
generic/templates/basic/generic/inclusion_tags/menu.html
generic/templates/basic/generic/inclusion_tags/navbar.html
generic/templates/basic/jmbo/inclusion_tags/modelbase_list_item.html
generic/templates/basic/jmbo/inclusion_tags/modelbase_pinned_list_item.html
generic/templates/basic/jmbo/inclusion_tags/pager.html
generic/templates/basic/registration/README.txt
generic/templates/basic/registration/logged_out.html
generic/templates/basic/registration/login.html
jmbo_generic.egg-info/PKG-INFO
jmbo_generic.egg-info/SOURCES.txt
jmbo_generic.egg-info/dependency_links.txt
jmbo_generic.egg-info/not-zip-safe
jmbo_generic.egg-info/requires.txt
jmbo_generic.egg-info/top_level.txt